blue_media
