Metadata-Version: 2.1
Name: blue_media
Version: 0.0.2
Summary: A wrapper of the api logic used to interact with blue_media.
Home-page: 
Author: ranyu
Author-email: wy176404@163.com
Classifier: Programming Language :: Python :: 3.6
Classifier: License :: OSI Approved :: MIT License
Classifier: Operating System :: OS Independent
License-File: LICENSE
Requires-Dist: aiohttp>=3.9.1
Requires-Dist: aiosignal>=1.3.1
Requires-Dist: async-timeout>=4.0.3
